MANIFEST.in
setup.py
artbrain/__init__.py
artbrain/art.py
artbrain/db.py
artbrain/hello.py
artbrain/scripts.py
artbrain/template.py
artbrain/utils.py
artbrain.egg-info/PKG-INFO
artbrain.egg-info/SOURCES.txt
artbrain.egg-info/dependency_links.txt
artbrain.egg-info/entry_points.txt
artbrain.egg-info/not-zip-safe
artbrain.egg-info/pbr.json
artbrain.egg-info/requires.txt
artbrain.egg-info/top_level.txt
artbrain/data/MNI152_T1_2mm_brain.nii.gz
artbrain/data/MNI152_T1_2mm_brain_mask.nii.gz
artbrain/templates/index.html