Metadata-Version: 1.0
Name: artbrain
Version: 1.0.1
Summary: embed images into brain imaging data
Home-page: http://www.github.com/vsoch/artbrain
Author: vsoch
Author-email: vsochat@stanford.edu
License: LICENSE.txt
Keywords: brain art neuroimaging
Platform: UNKNOWN
